huggingface_model_manager/__init__.py
huggingface_model_manager/model_manager.py
huggingface_model_manager-0.1.0.dist-info/METADATA
huggingface_model_manager-0.1.0.dist-info/WHEEL
huggingface_model_manager-0.1.0.dist-info/top_level.txt
huggingface_model_manager-0.1.0.dist-info/RECORD
