Metadata-Version: 2.1
Name: huggingface_model_manager
Version: 0.1.0
Summary: A library for saving, loading, and using Hugging Face models
Home-page: https://github.com/AnishKMBtech/huggingface_model_manager
Author: Your Name
Author-email: your.email@example.com
Classifier: Programming Language :: Python :: 3
Classifier: License :: OSI Approved :: MIT License
Classifier: Operating System :: OS Independent
Requires-Python: >=3.6
Requires-Dist: torch
Requires-Dist: transformers
